{"potential weakness": [{"SSI systemic meaning": {"id": 3, "subject": ["entity agent", "user", "owner", "holder", "entity subject"], "operation": ["countersink", "localize", "mark", "set", "limit", "jell", "define", "place", "lay out", "position", "lay", "localise", "coiffe", "ready", "coiffure", "specify", "do", "plant", "pose", "adjust", "congeal", "determine", "coif", "sic", "gear up", "fructify", "fix", "go down", "set up", "put", "typeset", "prepare", "rig", "go under", "correct", "dress", "arrange"], "data": [" resource", "variable", "environment variable"]}, "CWE weakness meaning": {"id": 688, "system component": ["software"], "system function": ["call", "specify"], "system object": ["function", "procedure", "routine", "variable", "reference"]}, "linguistic association": [{"first": "variable", "firstType": "data", "second": "variable", "secondType": "systemObject", "justification": ""}, {"first": "specify", "firstType": "operation", "second": "specify", "secondType": "systemFunction", "justification": ""}]}, {"SSI systemic meaning": {"id": 5, "subject": ["agent manager"], "operation": ["produce", "create", "make"], "data": ["key", "signing key", "public key", "encryption key", "identifier", "address", "did", "secret key", "private key", "id", "decentralized identifier"]}, "CWE weakness meaning": {"id": 211, "system component": ["application", "interpreter"], "system function": ["perform", "operate", "generate"], "system object": ["external diagnostic", "error message", "sensitive information"]}, "linguistic association": [{"first": "key", "firstType": "data", "second": "sensitive information", "secondType": "systemObject", "justification": ""}, {"first": "create", "firstType": "operation", "second": "generate", "secondType": "systemFunction", "justification": ""}]}, {"SSI systemic meaning": {"id": 6, "subject": ["blockchain service", "blockchain", "agent manager", " blockchain node"], "operation": ["publish", "compose", "indite", "drop a line", "spell", "pen", "save", "write"], "data": ["key", "signing key", "public key", "encryption key", "identifier", "address", "did", "secret key", "private key", "id", "decentralized identifier"]}, "CWE weakness meaning": {"id": 317, "system component": ["application"], "system function": ["store"], "system object": ["sensitive information", "cleartext"]}, "linguistic association": [{"first": "key", "firstType": "data", "second": "sensitive information", "secondType": "systemObject", "justification": ""}, {"first": "save", "firstType": "operation", "second": "store", "secondType": "systemFunction", "justification": ""}, {"first": "write", "firstType": "operation", "second": "store", "secondType": "systemFunction", "justification": ""}]}, {"SSI systemic meaning": {"id": 26, "subject": ["entity agent", "user", "owner", "holder", "entity subject"], "operation": ["furnish", "allow for", "put up", "render", "supply", "leave", "ply", "offer", "bring home the bacon", "allow", "cater", "provide"], "data": ["disclosure", "profile", "selective disclosure", "claim"]}, "CWE weakness meaning": {"id": 211, "system component": ["application", "interpreter"], "system function": ["perform", "operate", "generate"], "system object": ["external diagnostic", "error message", "sensitive information"]}, "linguistic association": [{"first": "claim", "firstType": "data", "second": "sensitive information", "secondType": "systemObject", "justification": ""}, {"first": "put up", "firstType": "operation", "second": "generate", "secondType": "systemFunction", "justification": ""}]}]}