{"potential weakness": [{"SSI systemic meaning": {"id": 3, "subject": ["entity agent", "user", "owner", "entity subject", "holder"], "operation": ["place", "localise", "ready", "set up", "countersink", "position", "typeset", "congeal", "dress", "rig", "coif", "pose", "put", "arrange", "fix", "gear up", "fructify", "do", "coiffe", "correct", "go under", "limit", "sic", "localize", "adjust", "mark", "define", "prepare", "determine", "coiffure", "jell", "lay out", "set", "lay", "go down", "specify", "plant"], "data": ["variable", "environment variable", " resource"]}, "CWE weakness meaning": {"id": 688, "system component": ["software"], "system function": ["call", "specify"], "system object": ["function", "procedure", "routine", "variable", "reference"]}, "linguistic association": [{"first": "variable", "firstType": "data", "second": "variable", "secondType": "systemObject", "justification": ""}, {"first": "specify", "firstType": "operation", "second": "specify", "secondType": "systemFunction", "justification": ""}]}, {"SSI systemic meaning": {"id": 5, "subject": ["agent manager"], "operation": ["create", "make", "produce"], "data": ["key", "decentralized identifier", "id", "address", "public key", "identifier", "did", "encryption key", "signing key", "secret key", "private key"]}, "CWE weakness meaning": {"id": 211, "system component": ["application", "interpreter"], "system function": ["perform", "operate", "generate"], "system object": ["external diagnostic", "error message", "sensitive information"]}, "linguistic association": [{"first": "key", "firstType": "data", "second": "sensitive information", "secondType": "systemObject", "justification": ""}, {"first": "create", "firstType": "operation", "second": "generate", "secondType": "systemFunction", "justification": ""}]}, {"SSI systemic meaning": {"id": 6, "subject": ["blockchain service", "blockchain", "agent manager", " blockchain node"], "operation": ["compose", "write", "pen", "save", "indite", "spell", "publish", "drop a line"], "data": ["key", "decentralized identifier", "id", "address", "public key", "identifier", "did", "encryption key", "signing key", "secret key", "private key"]}, "CWE weakness meaning": {"id": 317, "system component": ["application"], "system function": ["store"], "system object": ["sensitive information", "cleartext"]}, "linguistic association": [{"first": "key", "firstType": "data", "second": "sensitive information", "secondType": "systemObject", "justification": ""}, {"first": "write", "firstType": "operation", "second": "store", "secondType": "systemFunction", "justification": ""}, {"first": "save", "firstType": "operation", "second": "store", "secondType": "systemFunction", "justification": ""}]}]}